<databaseChangeLog xmlns="http://www.liquibase.org/xml/ns/dbchangelog"
                   xmlns:xsi="http://www.w3.org/2001/XMLSchema-instance"
                   xsi:schemaLocation="http://www.liquibase.org/xml/ns/dbchangelog
                    http://www.liquibase.org/xml/ns/dbchangelog/dbchangelog-3.1.xsd">

    <changeSet id="20220623210000" author="nankiewic">

        <createTable tableName="fuel_types">
            <column name="id" type="bigint" autoIncrement="true">
                <constraints primaryKey="true"/>

            </column>
            <column name="fuel_type" type="enum('PB98', 'PB95', 'LPG', 'ON')"/>
        </createTable>

        <createTable tableName="vehicle_makes">
            <column name="id" type="bigint" autoIncrement="true">
                <constraints primaryKey="true"/>
            </column>
            <column name="name" type="varchar(45)">
                <constraints nullable="false"/>
            </column>
        </createTable>

        <createTable tableName="insurance_types">
            <column name="id" type="bigint" autoIncrement="true">
                <constraints primaryKey="true"/>
            </column>
            <column name="insurance_type" type="enum('OC', 'AC', 'NNW')"/>
        </createTable>

        <createTable tableName="roles">
            <column name="id" type="bigint" autoIncrement="true">
                <constraints primaryKey="true"/>
            </column>
            <column name="role" type="enum('USER', 'SUPERUSER', 'ADMIN')"/>
        </createTable>

        <createTable tableName="user_account_status">
            <column name="id" type="bigint" autoIncrement="true">
                <constraints primaryKey="true"/>
            </column>
            <column name="account_status" type="enum('ACTIVE', 'INACTIVE', 'BLOCKED')"/>
        </createTable>

        <createTable tableName="vehicle_status">
            <column name="id" type="bigint" autoIncrement="true">
                <constraints primaryKey="true"/>
            </column>
            <column name="vehicle_status" type="enum('ACTIVE', 'REPAIR')"/>
        </createTable>

        <createTable tableName="users">
            <column name="id" type="bigint" autoIncrement="true">
                <constraints primaryKey="true"/>
            </column>
            <column name="email" type="varchar(45)">
                <constraints nullable="false"/>
            </column>
            <column name="password" type="varchar(255)">
                <constraints nullable="false"/>
            </column>
            <column name="reset_code" type="varchar(45)"/>
            <column name="reset_at" type="datetime"/>
            <column name="created_at" type="datetime"/>
            <column name="last_login_at" type="datetime"/>
            <column name="is_enabled" type="boolean" defaultValue="false"/>

            <column name="user_account_status_id" type="bigint">
                <constraints nullable="false"
                             foreignKeyName="fk_user_account_status"
                             references="user_account_status(id)"/>
            </column>
            <column name="roles_id" type="bigint">
                <constraints nullable="false"
                             foreignKeyName="fk_roles"
                             references="roles(id)"/>
            </column>
            <column name="manager_id" type="bigint">
                <constraints nullable="true"
                             foreignKeyName="fk_users_user"
                             references="users(id)"/>
            </column>
        </createTable>

        <createTable tableName="verification_token">
            <column name="id" type="bigint" autoIncrement="true">
                <constraints primaryKey="true"/>
            </column>
            <column name="token" type="varchar(255)">
                <constraints nullable="false"/>
            </column>
            <column name="expiry_date" type="datetime">
                <constraints nullable="false"/>
            </column>
            <column name="user_id" type="bigint">
                <constraints nullable="false"
                             foreignKeyName="fk_users_verification_token"
                             references="users(id)"/>
            </column>
        </createTable>

        <createTable tableName="address">
            <column name="id" type="bigint" autoIncrement="true">
                <constraints primaryKey="true"/>
            </column>
            <column name="city" type="varchar(45)">
                <constraints nullable="false"/>
            </column>
            <column name="street" type="varchar(45)"/>
            <column name="building_number" type="varchar(5)">
                <constraints nullable="false"/>
            </column>
            <column name="flat_number" type="varchar(7)"/>
            <column name="postal_code" type="varchar(7)">
                <constraints nullable="false"/>
            </column>
        </createTable>

        <createTable tableName="user_data">
            <column name="id" type="bigint" autoIncrement="true">
                <constraints primaryKey="true"/>
            </column>
            <column name="name" type="varchar(45)">
                <constraints nullable="false"/>
            </column>
            <column name="surname" type="varchar(45)">
                <constraints nullable="false"/>
            </column>
            <column name="phone_number" type="varchar(15)">
                <constraints nullable="false"/>
            </column>
            <column name="user_id" type="bigint">
                <constraints nullable="false"
                             foreignKeyName="fk_users_user_data"
                             references="users(id)"/>
            </column>
            <column name="address_id" type="bigint">
                <constraints nullable="false"
                             foreignKeyName="fk_address_user_data"
                             references="address(id)"/>
            </column>
        </createTable>

        <createTable tableName="vehicles">
            <column name="id" type="bigint" autoIncrement="true">
                <constraints primaryKey="true"/>
            </column>
            <column name="vehicle_make_id" type="bigint">
                <constraints nullable="false"
                             foreignKeyName="fk_vehicle_make_vehicle"
                             references="vehicle_makes(id)"/>
            </column>
            <column name="model" type="varchar(45)">
                <constraints nullable="false"/>
            </column>
            <column name="year" type="varchar(4)">
                <constraints nullable="false"/>
            </column>
            <column name="color" type="varchar(45)">
                <constraints nullable="false"/>
            </column>
            <column name="mileage" type="varchar(7)">
                <constraints nullable="false"/>
            </column>
            <column name="vin_number" type="varchar(17)">
                <constraints nullable="false"/>
            </column>
            <column name="vehicle_registration_number" type="varchar(10)">
                <constraints nullable="false"/>
            </column>

            <column name="fuel_type_id" type="bigint">
                <constraints nullable="false"
                             foreignKeyName="fk_fuel_types_vehicle"
                             references="fuel_types(id)"/>
            </column>
            <column name="city_fuel_consumption" type="decimal(4, 2)">
                <constraints nullable="false"/>
            </column>
            <column name="country_fuel_consumption" type="decimal(4, 2)">
                <constraints nullable="false"/>
            </column>
            <column name="average_fuel_consumption" type="decimal(4, 2)">
                <constraints nullable="false"/>
            </column>
            <column name="vehicle_status_id" type="bigint">
                <constraints nullable="false"
                             foreignKeyName="fk_vehicle_status_vehicle"
                             references="vehicle_status(id)"/>
            </column>
            <column name="user_id" type="bigint">
                <constraints nullable="false"
                             foreignKeyName="fk_users_vehicle"
                             references="users(id)"/>
            </column>
        </createTable>

        <createTable tableName="current_vehicle_users">
            <column name="id" type="bigint" autoIncrement="true">
                <constraints primaryKey="true"/>
            </column>

            <column name="user_id" type="bigint">
                <constraints nullable="false"
                             foreignKeyName="fk_users_current_vehicle_users"
                             references="users(id)"/>
            </column>
            <column name="vehicle_id" type="bigint">
                <constraints nullable="false"
                             foreignKeyName="fk_vehicles_current_vehicle_users"
                             references="vehicles(id)"/>
            </column>
        </createTable>

        <createTable tableName="vehicle_inspections">
            <column name="id" type="bigint" autoIncrement="true">
                <constraints primaryKey="true"/>
            </column>
            <column name="inspection_date" type="date">
                <constraints nullable="false"/>
            </column>
            <column name="expiration_date" type="date">
                <constraints nullable="false"/>
            </column>
            <column name="cost" type="decimal(5, 2)">
                <constraints nullable="false"/>
            </column>
            <column name="description" type="varchar(255)">
                <constraints nullable="true"/>
            </column>
            <column name="vehicle_id" type="bigint" >
                <constraints nullable="false"
                             foreignKeyName="fk_vehicles_vehicle_inspections"
                             references="vehicles(id)"/>
            </column>
        </createTable>

        <createTable tableName="vehicle_insurances">
            <column name="id" type="bigint" autoIncrement="true">
                <constraints primaryKey="true"/>
            </column>
            <column name="effective_date" type="date">
                <constraints nullable="false"/>
            </column>
            <column name="expiration_date" type="date">
                <constraints nullable="false"/>
            </column>
            <column name="cost" type="decimal(8, 2)">
                <constraints nullable="false"/>
            </column>
            <column name="policy_number" type="varchar(25)">
                <constraints nullable="false"/>
            </column>
            <column name="description" type="varchar(255)">
                <constraints nullable="true"/>
            </column>
            <column name="vehicle_id" type="bigint">
                <constraints nullable="false"
                             foreignKeyName="fk_vehicles"
                             references="vehicles(id)"/>
            </column>
            <column name="insurance_type_id" type="bigint">
                <constraints nullable="false"
                             foreignKeyName="fk_insurance_type_vehicle_insurances"
                             references="insurance_types(id)"/>
            </column>
        </createTable>

        <createTable tableName="vehicle_refueling">
            <column name="id" type="bigint" autoIncrement="true">
                <constraints primaryKey="true"/>
            </column>
            <column name="refueling_date" type="date">
                <constraints nullable="false"/>
            </column>
            <column name="litre" type="varchar(25)">
                <constraints nullable="false"/>
            </column>
            <column name="cost" type="decimal(8, 2)">
                <constraints nullable="false"/>
            </column>
            <column name="description" type="varchar(255)">
                <constraints nullable="true"/>
            </column>

            <column name="vehicle_id" type="bigint">
                <constraints nullable="false"
                             foreignKeyName="fk_vehicles_vehicle_refueling"
                             references="vehicles(id)"/>
            </column>
            <column name="user_id" type="bigint">
                <constraints nullable="false"
                             foreignKeyName="fk_users_vehicle_refueling"
                             references="users(id)"/>
            </column>
        </createTable>

        <createTable tableName="vehicle_repairs">
            <column name="id" type="bigint" autoIncrement="true">
                <constraints primaryKey="true"/>
            </column>
            <column name="repair_date" type="date">
                <constraints nullable="false"/>
            </column>
            <column name="description" type="varchar(555)">
                <constraints nullable="true"/>
            </column>
            <column name="cost" type="decimal(8, 2)">
                <constraints nullable="false"/>
            </column>
            <column name="title" type="varchar(20)">
                <constraints nullable="true"/>
            </column>
            <column name="vehicle_id" type="bigint">
                <constraints nullable="false"
                             foreignKeyName="fk_vehicles_vehicle_repairs"
                             references="vehicles(id)"/>
            </column>
        </createTable>

        <createTable tableName="vehicle_use">
            <column name="id" type="bigint" autoIncrement="true">
                <constraints primaryKey="true"/>
            </column>
            <column name="trip" type="smallint">
                <constraints nullable="false"/>
            </column>
            <column name="trip_date" type="date">
                <constraints nullable="false"/>
            </column>
            <column name="description" type="varchar(244)">
                <constraints nullable="true"/>
            </column>
            <column name="trip_type" type="varchar(7)">
                <constraints nullable="false"/>
            </column>

            <column name="vehicle_id" type="bigint">
                <constraints nullable="false"
                             foreignKeyName="fk_vehicles_vehicle_use"
                             references="vehicles(id)"/>
            </column>
            <column name="user_id" type="bigint">
                <constraints nullable="false"
                             foreignKeyName="fk_users_vehicle_use"
                             references="users(id)"/>
            </column>
        </createTable>

    </changeSet>
</databaseChangeLog>